openapi_client/__init__.py
openapi_client/api_client.py
openapi_client/api_response.py
openapi_client/configuration.py
openapi_client/exceptions.py
openapi_client/py.typed
openapi_client/rest.py
openapi_client/api/__init__.py
openapi_client/api/email_insights_api.py
openapi_client/api/ip_insights_api.py
openapi_client/models/__init__.py
openapi_client/models/abuse_contact.py
openapi_client/models/address_signals.py
openapi_client/models/admin_contact.py
openapi_client/models/analyze_email200_response.py
openapi_client/models/analyze_email400_response.py
openapi_client/models/analyze_email403_response.py
openapi_client/models/analyze_email500_response.py
openapi_client/models/analyze_email_request.py
openapi_client/models/analyze_ip200_response.py
openapi_client/models/analyze_ip400_response.py
openapi_client/models/analyze_ip_request.py
openapi_client/models/asn.py
openapi_client/models/batch_analyze_emails202_response.py
openapi_client/models/batch_analyze_emails400_response.py
openapi_client/models/batch_analyze_emails401_response.py
openapi_client/models/batch_analyze_emails402_response.py
openapi_client/models/batch_analyze_emails403_response.py
openapi_client/models/batch_analyze_emails413_response.py
openapi_client/models/batch_analyze_emails429_response.py
openapi_client/models/batch_analyze_emails_request.py
openapi_client/models/batch_analyze_ips202_response.py
openapi_client/models/batch_analyze_ips400_response.py
openapi_client/models/batch_analyze_ips_request.py
openapi_client/models/block_listed.py
openapi_client/models/create_email_batch_export400_response.py
openapi_client/models/create_email_batch_export403_response.py
openapi_client/models/create_email_batch_export404_response.py
openapi_client/models/create_email_batch_export409_response.py
openapi_client/models/email_dns.py
openapi_client/models/email_domain.py
openapi_client/models/export_created_response.py
openapi_client/models/export_filter.py
openapi_client/models/export_request.py
opportify_sdk-0.3.1.dist-info/METADATA
opportify_sdk-0.3.1.dist-info/WHEEL
opportify_sdk-0.3.1.dist-info/top_level.txt
opportify_sdk-0.3.1.dist-info/RECORD
