Metadata-Version: 2.4
Name: opportify_sdk
Version: 0.3.1
Summary: Opportify Insights API
Home-page: https://github.com/opportify/opportify-sdk-python
Author: Opportify & OpenAPI-Generator
Author-email: 
Keywords: OpenAPI,OpenAPI-Generator,Opportify Insights API,Opportify
Requires-Dist: urllib3<3.0.0,>=1.25.3
Requires-Dist: python-dateutil>=2.8.2
Requires-Dist: pydantic>=2
Requires-Dist: typing-extensions>=4.7.1
Dynamic: author
Dynamic: description
Dynamic: description-content-type
Dynamic: home-page
Dynamic: keywords
Dynamic: requires-dist
Dynamic: summary
